abspathlib.py
abspathlib-0.1.1.dist-info/METADATA
abspathlib-0.1.1.dist-info/WHEEL
abspathlib-0.1.1.dist-info/top_level.txt
abspathlib-0.1.1.dist-info/RECORD
