Metadata-Version: 2.1
Name: abspathlib
Version: 0.1.1
Summary: AbsPathLib is a library to manage absolute paths replicating pathlib interface
Home-page: https://github.com/josemvas/abspathlib
License: LGPLv3+
Keywords: absolute path library
Platform: UNKNOWN
Classifier: Programming Language :: Python :: 3 :: Only
Classifier: License :: OSI Approved :: GNU Lesser General Public License v3 or later (LGPLv3+)
Classifier: Operating System :: POSIX
Requires-Python: >=3.6
